metronome_rs-1.1.1.dist-info/METADATA
metronome_rs-1.1.1.dist-info/WHEEL
metronome_rs/__init__.py
metronome_rs/metronome_rs.cpython-312-darwin.so
metronome_rs-1.1.1.dist-info/RECORD
